{
    "device":{
       "attributes":[
          {
             "name":"MAC_ADDRESS",
             "value":"04bf6dafa4b0"
          },
          {
             "name":"MODEL",
             "value":"ZyXEL VMG1312-B10B"
          },
          {
             "name":"FIRMWARE",
             "value":"1.00(AALK.4)_TR143"
          }
       ],
       "id":"3414317575",
       "type":"XDSL_DATA_ACCESS",
       "resources":[
          {
             "attributes":[
                {
                   "name":"shelfName",
                   "value":"LURG1D"
                },
                {
                   "name":"shelfRack",
                   "value":""
                },
                {
                   "name":"ipAddress",
                   "value":"10.109.1.188"
                },
                {
                   "name":"ipNetworkElement",
                   "value":"LURG1D"
                },
                {
                   "name":"shelfType",
                   "value":"DSLAM CHASIS"
                },
                {
                   "name":"shelfHardware",
                   "value":"Huawei-MA5600"
                },
                {
                   "name":"clusterMember",
                   "value":""
                },
                {
                   "name":"slot",
                   "value":"15"
                },
                {
                   "name":"moduleName",
                   "value":"H569ADEE 15"
                },
                {
                   "name":"moduleHardware",
                   "value":"Huawei-H569ADEE"
                },
                {
                   "name":"portName",
                   "value":"0/15/42"
                },
                {
                   "name":"portType",
                   "value":"ADSL2+"
                },
                {
                   "name":"portState",
                   "value":"Active"
                },
                {
                   "name":"technicalProfile",
                   "value":"DLM_3552_608_DA"
                },
                {
                   "name":"commercialProfile",
                   "value":"ADSL-3M"
                }
             ],
             "id":"root:Locations:ARGENTINA:CAPITAL FEDERAL:CAPITAL FEDERAL:LUR:Sala Discover:LURG1D:LURG1D:15:H569ADEE 15:43",
             "type":"port"
          },
          {
            "attributes":[
               {
                  "name":"shelfName",
                  "value":"LURG1D"
               },
               {
                  "name":"shelfRack",
                  "value":""
               },
               {
                  "name":"ipAddress",
                  "value":"10.109.1.188"
               },
               {
                  "name":"ipNetworkElement",
                  "value":"LURG1D"
               },
               {
                  "name":"shelfType",
                  "value":"DSLAM CHASIS"
               },
               {
                  "name":"shelfHardware",
                  "value":"Huawei-MA5600"
               },
               {
                  "name":"clusterMember",
                  "value":""
               },
               {
                  "name":"slot",
                  "value":"15"
               },
               {
                  "name":"moduleName",
                  "value":"H569ADEE 15"
               },
               {
                  "name":"moduleHardware",
                  "value":"Huawei-H569ADEE"
               },
               {
                  "name":"portName",
                  "value":"0/15/42"
               },
               {
                  "name":"portType",
                  "value":"ADSL2+"
               },
               {
                  "name":"portState",
                  "value":"Active"
               },
               {
                  "name":"technicalProfile",
                  "value":"DLM_3552_608_DA"
               },
               {
                  "name":"commercialProfile",
                  "value":"ADSL-3M"
               }
            ],
            "id":"root:Locations:ARGENTINA:CAPITAL FEDERAL:CAPITAL FEDERAL:LUR:Sala Discover:LURG1D:LURG1D:15:H569ADEE 15:43",
            "type":"port"
         }
       ]
    }
 }